cs/resources.py
cs_resources-20250915.dist-info/WHEEL
cs_resources-20250915.dist-info/METADATA
cs_resources-20250915.dist-info/RECORD
