Metadata-Version: 2.4
Name: cs-resources
Version: 20250915
Summary: Resource management classes and functions.
Keywords: python2,python3
Author-email: Cameron Simpson <cs@cskk.id.au>
Classifier: Programming Language :: Python
Classifier: Programming Language :: Python :: 3
Classifier: Development Status :: 4 - Beta
Classifier: Intended Audience :: Developers
Classifier: Operating System :: OS Independent
Classifier: Topic :: Software Development :: Libraries :: Python Modules
Classifier: License :: OSI Approved :: GNU General Public License v3 or later (GPLv3+)
Requires-Dist: cs.context>=20250528
Requires-Dist: cs.deco>=20250914
Requires-Dist: cs.fsm>=20250120
Requires-Dist: cs.gimmicks>=20250428
Requires-Dist: cs.obj>=20250306
Requires-Dist: cs.pfx>=20250914
Requires-Dist: cs.psutils>=20250513
Requires-Dist: cs.py.func>=20250914
Requires-Dist: cs.py.stack>=20250724
Requires-Dist: cs.result>=20250306
Requires-Dist: cs.semantics>=20250103
Requires-Dist: cs.threads>=20250528
Requires-Dist: icontract
Requires-Dist: typeguard
Project-URL: MonoRepo Commits, https://bitbucket.org/cameron_simpson/css/commits/branch/main
Project-URL: Monorepo Git Mirror, https://github.com/cameron-simpson/css
Project-URL: Monorepo Hg/Mercurial Mirror, https://hg.sr.ht/~cameron-simpson/css
Project-URL: Source, https://github.com/cameron-simpson/css/blob/main/lib/python/cs/resources.py
